./.gitignore
./.python-version
./2378_process.log
./Dockerfile
./LICENSE
./PKG-INFO
./README.md
./docker-compose.yml
./entrypoint.sh
./fastn-server.py
./fastn.py
./language.json
./package_name
./push_info.json
./pyproject.toml
./uv.lock
./.claude/settings.local.json
iflow_mcp_fastnai_fastn-0.1.0.dist-info/METADATA
iflow_mcp_fastnai_fastn-0.1.0.dist-info/WHEEL
iflow_mcp_fastnai_fastn-0.1.0.dist-info/entry_points.txt
iflow_mcp_fastnai_fastn-0.1.0.dist-info/licenses/LICENSE
iflow_mcp_fastnai_fastn-0.1.0.dist-info/RECORD
