Metadata-Version: 2.4
Name: iflow-mcp_fastnai_fastn
Version: 0.1.0
Summary: A simple MCP fastn server
License-File: LICENSE
Requires-Python: >=3.10
Requires-Dist: httpx>=0.28.1
Requires-Dist: mcp[cli]>=1.2.0
